[
  {
    "category": "technology",
    "alias": "informatica",
    "name": "Informática",
    "title": "Tutoriales de informática",
    "description": "Cursos y tutoriales online de informática.",
    "image": "/images/tutoriales/tutoriales.jpg",
    "icon": "mdi-desktop-classic",
    "visible": true
  },
  {
    "category": "technology",
    "alias": "programacion",
    "name": "Programación",
    "title": "Tutoriales de programación",
    "description": "Cursos y tutoriales online de programación.",
    "image": "/images/tutoriales/tutoriales.jpg",
    "icon": "mdi-code-tags",
    "visible": true
  },
  {
    "category": "technology",
    "alias": "electronica",
    "name": "Electrónica",
    "title": "Tutoriales de electrónica",
    "description": "Cursos y tutoriales online de electrónica.",
    "image": "/images/tutoriales/tutoriales.jpg",
    "icon": "mdi-chip",
    "visible": true
  },
  {
    "category": "technology",
    "alias": "robotica-educativa",
    "name": "Robótica educativa",
    "title": "Tutoriales de Robótica educativa",
    "description": "Cursos y tutoriales de robótica educativa.",
    "image": "/images/tutoriales/robotica-educativa.jpg",
    "icon": "mdi-robot",
    "visible": true
  },
  {
    "category": "technology",
    "alias": "realidad-aumentada",
    "name": "Realidad aumentada",
    "title": "Tutoriales de Realidad aumentada con Scratch",
    "description": "Cursos y tutoriales online para aprender a programar Realidad aumentada con Scratch.",
    "image": "/images/tutoriales/scratch.jpg",
    "icon": "mdi-augmented-reality",
    "visible": true
  },
  {
    "category": "technology",
    "alias": "impresion-3d",
    "name": "Impresión 3D",
    "title": "Tutoriales de Impresión 3D",
    "description": "Cursos y tutoriales de impresión 3D para makers desde cero.",
    "image": "/images/tutoriales/impresion-3d.jpg",
    "icon": "mdi-printer-3d-nozzle",
    "visible": true
  },
  {
    "category": "technology",
    "alias": "unplugged",
    "name": "Unplugged",
    "title": "Tutoriales de programación desenchufada",
    "description": "Cursos y tutoriales para aprender a programar sin ordenador.",
    "image": "/images/tutoriales/tutoriales.jpg",
    "icon": "mdi-power-plug-off",
    "visible": true
  },





  {
    "category": "hardware",
    "alias": "makey-makey",
    "name": "Makey-Makey",
    "title": "Tutoriales de Makey-Makey",
    "description": "Cursos y tutoriales de Makey-Makey.",
    "image": "/images/tutoriales/makey-makey.jpg",
    "icon": "mdi-chip",
    "visible": true
  },
  {
    "category": "hardware",
    "alias": "mbot",
    "name": "Robot mBot",
    "title": "Tutoriales de mBot",
    "description": "Cursos y tutoriales de robótica educativa con mBot.",
    "image": "/images/tutoriales/mbot.jpg",
    "icon": "mdi-car-electric",
    "visible": true
  },
  {
    "category": "hardware",
    "alias": "arduino",
    "name": "Arduino",
    "title": "Tutoriales de Arduino",
    "description": "Cursos y tutoriales de programación y electrónica de placas Arduino.",
    "image": "/images/tutoriales/arduino.jpg",
    "icon": "mdi-code-braces",
    "visible": true
  },
  {
    "category": "hardware",
    "alias": "raspberry-pi",
    "name": "Raspberry Pi",
    "title": "Tutoriales con Raspberry Pi",
    "description": "Cursos y tutoriales de informática utilizando la Raspberry Pi.",
    "image": "/images/tutoriales/raspberry-pi.jpg",
    "icon": "mdi-raspberry-pi",
    "visible": true
  },
  {
    "category": "hardware",
    "alias": "microbit",
    "name": "Micro:bit",
    "title": "Tutoriales con Micro:bit",
    "description": "Cursos y tutoriales de programación y electrónica con Micro:bit.",
    "image": "/images/tutoriales/microbit.jpg",
    "icon": "mdi-chip",
    "visible": true
  },





  {
    "category": "software",
    "alias": "scratch",
    "name": "Scratch",
    "title": "Tutoriales de Scratch",
    "description": "Cursos y tutoriales online para aprender a programar con Scratch.",
    "image": "/images/tutoriales/scratch.jpg",
    "icon": "mdi-code-string",
    "visible": true
  },
  {
    "category": "software",
    "alias": "mblock",
    "name": "mBlock",
    "title": "Tutoriales de mBlock",
    "description": "Cursos y tutoriales de programación y electrónica con mBlock.",
    "image": "/images/tutoriales/mblock.jpg",
    "icon": "mdi-code-array",
    "visible": true
  },
  {
    "category": "software",
    "alias": "appinventor",
    "name": "App-Inventor",
    "title": "Tutoriales de AppInventor",
    "description": "Cursos y tutoriales para aprender a programar con AppInventor.",
    "image": "/images/tutoriales/appinventor.jpg",
    "icon": "mdi-tablet-android",
    "visible": true
  },
  {
    "category": "software",
    "alias": "python",
    "name": "Python",
    "title": "Tutoriales de Python con Raspberry Pi",
    "description": "Cursos y tutoriales de informática utilizando la Raspberry Pi.",
    "image": "/images/tutoriales/raspberry-pi.jpg",
    "icon": "mdi-language-python",
    "visible": true
  },
  




  {
    "category": "others",
    "alias": "videojuegos",
    "name": "Videojuegos",
    "title": "Tutoriales de videojuegos",
    "description": "Cursos y tutoriales online para aprender a programar videojuegos.",
    "image": "/images/tutoriales/scratch.jpg",
    "icon": "mdi-gamepad",
    "visible": false
  },
  {
    "category": "others",
    "alias": "gpio",
    "name": "Pines GPIO",
    "title": "Tutoriales de electrónica con Raspberry Pi",
    "description": "Cursos y tutoriales de informática utilizando la Raspberry Pi.",
    "image": "/images/tutoriales/raspberry-pi.jpg",
    "icon": "mdi-car-battery",
    "visible": false
  },
  {
    "category": "others",
    "alias": "tinkercad",
    "name": "TinkerCAD",
    "title": "Tutoriales de TinkerCAD",
    "description": "Cursos y tutoriales de TinkerCAD para makers desde cero.",
    "image": "/images/tutoriales/tinkercad.jpg",
    "icon": "mdi-printer-3d",
    "visible": false
  },
  {
    "category": "others",
    "alias": "paginas-web",
    "name": "Páginas web",
    "title": "Tutoriales de páginas web.",
    "description": "Cursos y tutoriales para aprender a programar páginas web.",
    "image": "/images/tutoriales/paginas-web.jpg",
    "icon": "mdi-language-html5",
    "visible": false
  }
]